{
  "AGLT2": [
    {
      "affected_services": "CE", 
      "classification": "SCHEDULED", 
      "create_time": "2018-07-18T18:00:47.990517", 
      "description": "Turning down/off our SL6 queues, hopefully permanently", 
      "end_time": "2038-01-19T03:14:00", 
      "id": 124432, 
      "info_url": "", 
      "is_published": false, 
      "last_modified": "2018-08-01T22:00:28.249550", 
      "last_published": null, 
      "pid": "1005688", 
      "provider": "OIM", 
      "rc_site": "AGLT2", 
      "services": [], 
      "severity": "OUTAGE", 
      "site": "AGLT2", 
      "site_id": 1296, 
      "start_time": "2018-07-11T13:00:00", 
      "state": "ACTIVE"
    }
  ], 
  "CA-SCINET-T2": [
    {
      "affected_services": "APEL, CREAM-CE, gLExec, gLite-APEL", 
      "classification": "UNSCHEDULED", 
      "create_time": "2018-05-02T18:37:11", 
      "description": "Site is being decommissioned.  No compute available anymore.  Storage almost drained", 
      "end_time": "2018-12-31T23:59:00", 
      "id": 124140, 
      "info_url": "https://goc.egi.eu/portal/index.php?Page_Type=Downtime&id=25270", 
      "is_published": false, 
      "last_modified": "2018-05-02T20:45:05.254843", 
      "last_published": null, 
      "pid": "103882G0", 
      "provider": "GOCDB", 
      "rc_site": "CA-SCINET-T2", 
      "services": [], 
      "severity": "OUTAGE", 
      "site": "CA-SCINET-T2", 
      "site_id": 1280, 
      "start_time": "2018-04-30T20:00:00", 
      "state": "ACTIVE"
    }
  ], 
  "CA-WATERLOO-T2": [
    {
      "affected_services": "APEL, ARC-CE, SRM, Site-BDII, gLite-APEL, net.perfSONAR.Bandwidth, net.perfSONAR.Latency, org.squid-cache.Squid", 
      "classification": "UNSCHEDULED", 
      "create_time": "2018-09-01T00:56:04", 
      "description": "Power restored but no cooling yet, so no services available until Tuesday (after North America Labour Day)", 
      "end_time": "2018-09-14T23:59:00", 
      "id": 124588, 
      "info_url": "https://goc.egi.eu/portal/index.php?Page_Type=Downtime&id=25983", 
      "is_published": false, 
      "last_modified": "2018-09-01T03:00:12.336823", 
      "last_published": null, 
      "pid": "104596G0", 
      "provider": "GOCDB", 
      "rc_site": "CA-WATERLOO-T2", 
      "services": [
        {
          "endpoint": "lcg-ce1.uw.computecanada.ca", 
          "flavour": "ARC-CE", 
          "id": 18246, 
          "last_modified": "2018-04-25T18:33:25.629830", 
          "name": "CA-WATERLOO-T2-CE-lcg-ce1.uw.computecanada.ca", 
          "site": "CA-WATERLOO-T2", 
          "state": "ACTIVE", 
          "state_comment": "automatically collected from GOCDB/OIM source", 
          "state_update": "2018-04-25T18:33:25.629722", 
          "status": "production", 
          "type": "CE"
        }, 
        {
          "endpoint": "lcg-psbw.uw.computecanada.ca", 
          "flavour": "Bandwidth", 
          "id": 18177, 
          "last_modified": "2017-12-12T00:31:57.072967", 
          "name": "CA-WATERLOO-T2-PerfSonar-Bandwidth-lcg-psbw.uw.computecanada.ca", 
          "site": "CA-WATERLOO-T2", 
          "state": "ACTIVE", 
          "state_comment": "automatically collected from GOCDB/OIM source (ACTIVE by default)", 
          "state_update": "2017-12-12T00:31:57", 
          "status": "production", 
          "type": "PerfSonar"
        }, 
        {
          "endpoint": "lcg-pslat.uw.computecanada.ca", 
          "flavour": "Latency", 
          "id": 18176, 
          "last_modified": "2017-12-12T00:31:57.037147", 
          "name": "CA-WATERLOO-T2-PerfSonar-Latency-lcg-pslat.uw.computecanada.ca", 
          "site": "CA-WATERLOO-T2", 
          "state": "ACTIVE", 
          "state_comment": "automatically collected from GOCDB/OIM source (ACTIVE by default)", 
          "state_update": "2017-12-12T00:31:56", 
          "status": "production", 
          "type": "PerfSonar"
        }, 
        {
          "endpoint": "srm://lcg-se1.uw.computecanada.ca:8443/srm/managerv2?SFN=", 
          "flavour": "SRM", 
          "id": 17967, 
          "last_modified": "2017-11-14T21:06:42.906981", 
          "name": "CA-WATERLOO-T2-SRM-lcg-se1.uw.computecanada.ca", 
          "site": "CA-WATERLOO-T2", 
          "state": "ACTIVE", 
          "state_comment": "State set to ACTIVE after DDMEndpoint creation", 
          "state_update": "2017-11-01T03:37:51.138491", 
          "status": "production", 
          "type": "SRM"
        }, 
        {
          "endpoint": "http://lcg-adm2.uw.computecanada.ca:3128", 
          "flavour": "CVMFS", 
          "id": 18248, 
          "last_modified": "2018-04-25T17:11:32.367007", 
          "name": "CA-WATERLOO-T2-CVMFS-lcg-adm2.uw.computecanada.ca", 
          "site": "CA-WATERLOO-T2", 
          "state": "ACTIVE", 
          "state_comment": "Service created by using WebUI", 
          "state_update": "2018-04-25T17:11:21.218625", 
          "status": "", 
          "type": "Squid"
        }
      ], 
      "severity": "OUTAGE", 
      "site": "CA-WATERLOO-T2", 
      "site_id": 5443, 
      "start_time": "2018-08-31T23:59:00", 
      "state": "ACTIVE"
    }
  ], 
  "CSCS-LCG2": [
    {
      "affected_services": "APEL, ARC-CE, gLite-APEL", 
      "classification": "SCHEDULED", 
      "create_time": "2018-09-03T12:30:21", 
      "description": "Scheduled Maintenance on Piz Daint", 
      "end_time": "2018-09-12T19:00:00", 
      "id": 124592, 
      "info_url": "https://goc.egi.eu/portal/index.php?Page_Type=Downtime&id=25988", 
      "is_published": false, 
      "last_modified": "2018-09-03T14:45:06.603020", 
      "last_published": null, 
      "pid": "104601G0", 
      "provider": "GOCDB", 
      "rc_site": "CSCS-LCG2", 
      "services": [
        {
          "endpoint": "arc04.lcg.cscs.ch:2811", 
          "flavour": "ARC-CE", 
          "id": 17862, 
          "last_modified": "2017-04-12T12:15:29.792761", 
          "name": "CSCS-LCG2-CE-arc04.lcg.cscs.ch", 
          "site": "CSCS-LCG2", 
          "state": "ACTIVE", 
          "state_comment": "Auto ENABLED since the queue=wlcg is attached to the PandaQueue CSCS-LCG2-HPC", 
          "state_update": "2017-04-12T12:15:29.792649", 
          "status": "production", 
          "type": "CE"
        }
      ], 
      "severity": "OUTAGE", 
      "site": "CSCS-LCG2", 
      "site_id": 1286, 
      "start_time": "2018-09-12T05:00:00", 
      "state": "ACTIVE"
    }
  ], 
  "DESY-HH": [
    {
      "affected_services": "CREAM-CE", 
      "classification": "SCHEDULED", 
      "create_time": "2018-08-22T13:20:26", 
      "description": "Start of gradual retirement of grid-cr{0,1}.desy.de", 
      "end_time": "2018-09-30T23:59:00", 
      "id": 124564, 
      "info_url": "https://goc.egi.eu/portal/index.php?Page_Type=Downtime&id=25899", 
      "is_published": false, 
      "last_modified": "2018-08-22T15:30:08.050857", 
      "last_published": null, 
      "pid": "104512G0", 
      "provider": "GOCDB", 
      "rc_site": "DESY-HH", 
      "services": [], 
      "severity": "WARNING", 
      "site": "DESY-HH", 
      "site_id": 1202, 
      "start_time": "2018-09-01T00:00:00", 
      "state": "ACTIVE"
    }, 
    {
      "affected_services": "ARC-CE, gLite-APEL", 
      "classification": "SCHEDULED", 
      "create_time": "2018-08-28T14:58:37", 
      "description": "cross warning for Belle and ILC if implicitly using the DESY SE by using the CEs: annual maintenance and upgrade of the SE", 
      "end_time": "2018-09-12T17:00:00", 
      "id": 124579, 
      "info_url": "https://goc.egi.eu/portal/index.php?Page_Type=Downtime&id=25932", 
      "is_published": false, 
      "last_modified": "2018-08-28T17:00:13.245793", 
      "last_published": null, 
      "pid": "104545G0", 
      "provider": "GOCDB", 
      "rc_site": "DESY-HH", 
      "services": [
        {
          "endpoint": "grid-arcce0.desy.de:2811", 
          "flavour": "ARC-CE", 
          "id": 17434, 
          "last_modified": "2017-01-30T14:29:04.244909", 
          "name": "DESY-HH-CE-grid-arcce0.desy.de", 
          "site": "DESY-HH", 
          "state": "ACTIVE", 
          "state_comment": "automatically collected from GOCDB/OIM source", 
          "state_update": "2017-01-30T14:29:04.244825", 
          "status": "production", 
          "type": "CE"
        }, 
        {
          "endpoint": "grid-arcce1.desy.de:2811", 
          "flavour": "ARC-CE", 
          "id": 17592, 
          "last_modified": "2016-10-17T15:42:04.940418", 
          "name": "DESY-HH-CE-grid-arcce1.desy.de", 
          "site": "DESY-HH", 
          "state": "ACTIVE", 
          "state_comment": "automatically collected from GOCDB/OIM source", 
          "state_update": "2016-10-17T15:42:04.940318", 
          "status": "production", 
          "type": "CE"
        }
      ], 
      "severity": "WARNING", 
      "site": "DESY-HH", 
      "site_id": 1202, 
      "start_time": "2018-09-12T07:00:00", 
      "state": "ACTIVE"
    }, 
    {
      "affected_services": "SRM", 
      "classification": "SCHEDULED", 
      "create_time": "2018-08-28T14:53:49", 
      "description": "DESY SE downtime", 
      "end_time": "2018-09-12T17:00:00", 
      "id": 124577, 
      "info_url": "https://goc.egi.eu/portal/index.php?Page_Type=Downtime&id=25930", 
      "is_published": false, 
      "last_modified": "2018-08-28T17:00:11.622190", 
      "last_published": null, 
      "pid": "104543G0", 
      "provider": "GOCDB", 
      "rc_site": "DESY-HH", 
      "services": [], 
      "severity": "OUTAGE", 
      "site": "DESY-HH", 
      "site_id": 1202, 
      "start_time": "2018-09-12T07:00:00", 
      "state": "ACTIVE"
    }
  ], 
  "GR-01-AUTH": [
    {
      "affected_services": "APEL, CREAM-CE, SRM, Site-BDII, emi.ARGUS, eu.egi.MPI, eu.egi.storage.accounting, gLExec, gLite-APEL", 
      "classification": "SCHEDULED", 
      "create_time": "2018-06-11T08:42:00", 
      "description": "GR-01-AUTH decomission", 
      "end_time": "2018-09-11T23:59:00", 
      "id": 124291, 
      "info_url": "https://goc.egi.eu/portal/index.php?Page_Type=Downtime&id=25449", 
      "is_published": false, 
      "last_modified": "2018-06-11T10:45:04.948941", 
      "last_published": null, 
      "pid": "104061G0", 
      "provider": "GOCDB", 
      "rc_site": "GR-01-AUTH", 
      "services": [
        {
          "endpoint": "cream01.grid.auth.gr:8443", 
          "flavour": "CREAM-CE", 
          "id": 6501, 
          "last_modified": "2015-01-29T17:01:35.437264", 
          "name": "GR-01-AUTH-CE-cream01.grid.auth.gr", 
          "site": "GR-01-AUTH", 
          "state": "ACTIVE", 
          "state_comment": "automatically collected from GOCDB/OIM sources", 
          "state_update": "2012-11-17T00:01:32.091431", 
          "status": "production", 
          "type": "CE"
        }, 
        {
          "endpoint": "srm://se01.grid.auth.gr:8446/srm/managerv2?SFN=", 
          "flavour": "SRM", 
          "id": 2404, 
          "last_modified": "2015-01-29T17:01:30.403798", 
          "name": "GR-01-AUTH-SRM-se01.grid.auth.gr", 
          "site": "GR-01-AUTH", 
          "state": "ACTIVE", 
          "state_comment": "", 
          "state_update": null, 
          "status": "production", 
          "type": "SRM"
        }
      ], 
      "severity": "OUTAGE", 
      "site": "GR-01-AUTH", 
      "site_id": 1302, 
      "start_time": "2018-06-26T00:00:00", 
      "state": "ACTIVE"
    }
  ], 
  "HEPHY-UIBK": [
    {
      "affected_services": "APEL, CREAM-CE, gLExec", 
      "classification": "SCHEDULED", 
      "create_time": "2018-08-28T09:15:32", 
      "description": "hardware issue after maintenance reboot", 
      "end_time": "2018-09-29T20:00:00", 
      "id": 124575, 
      "info_url": "https://goc.egi.eu/portal/index.php?Page_Type=Downtime&id=25927", 
      "is_published": false, 
      "last_modified": "2018-08-28T11:30:07.141321", 
      "last_published": null, 
      "pid": "104540G0", 
      "provider": "GOCDB", 
      "rc_site": "HEPHY-UIBK", 
      "services": [], 
      "severity": "OUTAGE", 
      "site": "HEPHY-UIBK", 
      "site_id": 1277, 
      "start_time": "2018-09-01T20:00:00", 
      "state": "ACTIVE"
    }
  ], 
  "IN2P3-CC": [
    {
      "affected_services": "CREAM-CE, Central-LFC, SRM, SRM.nearline, Site-BDII, Top-BDII, VOMS, XRootD.Redirector, emi.ARGUS, gLExec, gLite-APEL, net.perfSONAR.Bandwidth, net.perfSONAR.Latency, ngi.SAM, org.squid-cache.Squid", 
      "classification": "SCHEDULED", 
      "create_time": "2017-09-20T13:03:50", 
      "description": "Scheduled site maintenance. More details during the month before the outage.", 
      "end_time": "2018-09-18T23:00:00", 
      "id": 123288, 
      "info_url": "https://goc.egi.eu/portal/index.php?Page_Type=Downtime&id=24010", 
      "is_published": false, 
      "last_modified": "2017-09-20T15:15:05.765105", 
      "last_published": null, 
      "pid": "102601G0", 
      "provider": "GOCDB", 
      "rc_site": "IN2P3-CC", 
      "services": [
        {
          "endpoint": "cccreamceli05.in2p3.fr:8443", 
          "flavour": "CREAM-CE", 
          "id": 2620, 
          "last_modified": "2018-04-09T22:30:37.830087", 
          "name": "IN2P3-CC-CE-cccreamceli05.in2p3.fr", 
          "site": "IN2P3-CC", 
          "state": "ACTIVE", 
          "state_comment": "Auto ENABLED since the queue=long is attached to the PandaQueue ANALY_IN2P3-CC_CL7", 
          "state_update": "2018-04-09T22:30:37.830032", 
          "status": "production", 
          "type": "CE"
        }, 
        {
          "endpoint": "cccreamceli01.in2p3.fr:8443", 
          "flavour": "CREAM-CE", 
          "id": 2822, 
          "last_modified": "2018-06-04T11:32:01.920263", 
          "name": "IN2P3-CC-CE-TEST-cccreamceli01.in2p3.fr", 
          "site": "IN2P3-CC", 
          "state": "ACTIVE", 
          "state_comment": "Auto ENABLED since the queue=long is attached to the PandaQueue IN2P3-CC_CL7", 
          "state_update": "2018-06-04T11:32:01.920212", 
          "status": "production", 
          "type": "CE"
        }, 
        {
          "endpoint": "cccreamceli04.in2p3.fr:8443", 
          "flavour": "CREAM-CE", 
          "id": 14263, 
          "last_modified": "2018-03-21T20:59:12.971140", 
          "name": "IN2P3-CC-CE-cccreamceli04.in2p3.fr", 
          "site": "IN2P3-CC", 
          "state": "ACTIVE", 
          "state_comment": "Auto ENABLED since the queue=long is attached to the PandaQueue IN2P3-CC_CL7", 
          "state_update": "2018-03-21T20:59:12.971045", 
          "status": "production", 
          "type": "CE"
        }, 
        {
          "endpoint": "cccreamceli03.in2p3.fr:8443", 
          "flavour": "CREAM-CE", 
          "id": 17536, 
          "last_modified": "2016-06-01T10:22:14.710032", 
          "name": "IN2P3-CC-CE-cccreamceli03.in2p3.fr", 
          "site": "IN2P3-CC", 
          "state": "ACTIVE", 
          "state_comment": "Auto ENABLED since the queue=mc_long is attached to the PandaQueue IN2P3-CC_MCORE", 
          "state_update": "2016-06-01T10:22:14.709941", 
          "status": "production", 
          "type": "CE"
        }, 
        {
          "endpoint": "ccperfsonar1.in2p3.fr", 
          "flavour": "Bandwidth", 
          "id": 14404, 
          "last_modified": "2015-01-29T17:01:37.285208", 
          "name": "IN2P3-CC-PerfSonar-Bandwidth-ccperfsonar1.in2p3.fr", 
          "site": "IN2P3-CC", 
          "state": "ACTIVE", 
          "state_comment": "automatically collected from GOCDB/OIM source (ACTIVE by default)", 
          "state_update": "2014-03-25T18:01:28.965152", 
          "status": "production", 
          "type": "PerfSonar"
        }, 
        {
          "endpoint": "ccperfsonar2.in2p3.fr", 
          "flavour": "Latency", 
          "id": 14405, 
          "last_modified": "2015-01-29T17:01:37.839072", 
          "name": "IN2P3-CC-PerfSonar-Latency-ccperfsonar2.in2p3.fr", 
          "site": "IN2P3-CC", 
          "state": "ACTIVE", 
          "state_comment": "automatically collected from GOCDB/OIM source (ACTIVE by default)", 
          "state_update": "2014-03-25T18:01:29.068389", 
          "status": "production", 
          "type": "PerfSonar"
        }, 
        {
          "endpoint": "srm://ccsrm.in2p3.fr:8443/srm/managerv2?SFN=", 
          "flavour": "SRM", 
          "id": 2394, 
          "last_modified": "2015-01-29T17:01:29.169832", 
          "name": "IN2P3-CC-SRM-ccsrm.in2p3.fr", 
          "site": "IN2P3-CC", 
          "state": "ACTIVE", 
          "state_comment": "", 
          "state_update": null, 
          "status": "production", 
          "type": "SRM"
        }
      ], 
      "severity": "OUTAGE", 
      "site": "IN2P3-CC", 
      "site_id": 1256, 
      "start_time": "2018-09-18T05:00:00", 
      "state": "ACTIVE"
    }, 
    {
      "affected_services": "CREAM-CE, Central-LFC, SRM, SRM.nearline, Site-BDII, Top-BDII, VOMS, XRootD.Redirector, emi.ARGUS, eu.egi.storage.accounting, gLExec, gLite-APEL, net.perfSONAR.Bandwidth, net.perfSONAR.Latency, ngi.SAM, org.squid-cache.Squid", 
      "classification": "SCHEDULED", 
      "create_time": "2017-12-06T10:21:38", 
      "description": "Scheduled site maintenance. More details during the month before the outage", 
      "end_time": "2018-12-04T21:00:00", 
      "id": 123571, 
      "info_url": "https://goc.egi.eu/portal/index.php?Page_Type=Downtime&id=24460", 
      "is_published": false, 
      "last_modified": "2017-12-06T11:30:06.268550", 
      "last_published": null, 
      "pid": "103051G0", 
      "provider": "GOCDB", 
      "rc_site": "IN2P3-CC", 
      "services": [
        {
          "endpoint": "cccreamceli05.in2p3.fr:8443", 
          "flavour": "CREAM-CE", 
          "id": 2620, 
          "last_modified": "2018-04-09T22:30:37.830087", 
          "name": "IN2P3-CC-CE-cccreamceli05.in2p3.fr", 
          "site": "IN2P3-CC", 
          "state": "ACTIVE", 
          "state_comment": "Auto ENABLED since the queue=long is attached to the PandaQueue ANALY_IN2P3-CC_CL7", 
          "state_update": "2018-04-09T22:30:37.830032", 
          "status": "production", 
          "type": "CE"
        }, 
        {
          "endpoint": "cccreamceli01.in2p3.fr:8443", 
          "flavour": "CREAM-CE", 
          "id": 2822, 
          "last_modified": "2018-06-04T11:32:01.920263", 
          "name": "IN2P3-CC-CE-TEST-cccreamceli01.in2p3.fr", 
          "site": "IN2P3-CC", 
          "state": "ACTIVE", 
          "state_comment": "Auto ENABLED since the queue=long is attached to the PandaQueue IN2P3-CC_CL7", 
          "state_update": "2018-06-04T11:32:01.920212", 
          "status": "production", 
          "type": "CE"
        }, 
        {
          "endpoint": "cccreamceli04.in2p3.fr:8443", 
          "flavour": "CREAM-CE", 
          "id": 14263, 
          "last_modified": "2018-03-21T20:59:12.971140", 
          "name": "IN2P3-CC-CE-cccreamceli04.in2p3.fr", 
          "site": "IN2P3-CC", 
          "state": "ACTIVE", 
          "state_comment": "Auto ENABLED since the queue=long is attached to the PandaQueue IN2P3-CC_CL7", 
          "state_update": "2018-03-21T20:59:12.971045", 
          "status": "production", 
          "type": "CE"
        }, 
        {
          "endpoint": "cccreamceli03.in2p3.fr:8443", 
          "flavour": "CREAM-CE", 
          "id": 17536, 
          "last_modified": "2016-06-01T10:22:14.710032", 
          "name": "IN2P3-CC-CE-cccreamceli03.in2p3.fr", 
          "site": "IN2P3-CC", 
          "state": "ACTIVE", 
          "state_comment": "Auto ENABLED since the queue=mc_long is attached to the PandaQueue IN2P3-CC_MCORE", 
          "state_update": "2016-06-01T10:22:14.709941", 
          "status": "production", 
          "type": "CE"
        }, 
        {
          "endpoint": "ccperfsonar1.in2p3.fr", 
          "flavour": "Bandwidth", 
          "id": 14404, 
          "last_modified": "2015-01-29T17:01:37.285208", 
          "name": "IN2P3-CC-PerfSonar-Bandwidth-ccperfsonar1.in2p3.fr", 
          "site": "IN2P3-CC", 
          "state": "ACTIVE", 
          "state_comment": "automatically collected from GOCDB/OIM source (ACTIVE by default)", 
          "state_update": "2014-03-25T18:01:28.965152", 
          "status": "production", 
          "type": "PerfSonar"
        }, 
        {
          "endpoint": "ccperfsonar2.in2p3.fr", 
          "flavour": "Latency", 
          "id": 14405, 
          "last_modified": "2015-01-29T17:01:37.839072", 
          "name": "IN2P3-CC-PerfSonar-Latency-ccperfsonar2.in2p3.fr", 
          "site": "IN2P3-CC", 
          "state": "ACTIVE", 
          "state_comment": "automatically collected from GOCDB/OIM source (ACTIVE by default)", 
          "state_update": "2014-03-25T18:01:29.068389", 
          "status": "production", 
          "type": "PerfSonar"
        }, 
        {
          "endpoint": "srm://ccsrm.in2p3.fr:8443/srm/managerv2?SFN=", 
          "flavour": "SRM", 
          "id": 2394, 
          "last_modified": "2015-01-29T17:01:29.169832", 
          "name": "IN2P3-CC-SRM-ccsrm.in2p3.fr", 
          "site": "IN2P3-CC", 
          "state": "ACTIVE", 
          "state_comment": "", 
          "state_update": null, 
          "status": "production", 
          "type": "SRM"
        }
      ], 
      "severity": "OUTAGE", 
      "site": "IN2P3-CC", 
      "site_id": 1256, 
      "start_time": "2018-12-04T07:00:00", 
      "state": "ACTIVE"
    }, 
    {
      "affected_services": "CREAM-CE, Central-LFC, SRM, SRM.nearline, Site-BDII, Top-BDII, VOMS, XRootD.Redirector, emi.ARGUS, eu.egi.storage.accounting, gLExec, gLite-APEL, net.perfSONAR.Bandwidth, net.perfSONAR.Latency, ngi.SAM, org.squid-cache.Squid", 
      "classification": "SCHEDULED", 
      "create_time": "2018-03-19T10:15:54", 
      "description": "Scheduled site maintenance. More details during the month before the outage.", 
      "end_time": "2019-03-12T23:00:00", 
      "id": 123974, 
      "info_url": "https://goc.egi.eu/portal/index.php?Page_Type=Downtime&id=25059", 
      "is_published": false, 
      "last_modified": "2018-03-19T11:30:05.778952", 
      "last_published": null, 
      "pid": "103671G0", 
      "provider": "GOCDB", 
      "rc_site": "IN2P3-CC", 
      "services": [
        {
          "endpoint": "cccreamceli05.in2p3.fr:8443", 
          "flavour": "CREAM-CE", 
          "id": 2620, 
          "last_modified": "2018-04-09T22:30:37.830087", 
          "name": "IN2P3-CC-CE-cccreamceli05.in2p3.fr", 
          "site": "IN2P3-CC", 
          "state": "ACTIVE", 
          "state_comment": "Auto ENABLED since the queue=long is attached to the PandaQueue ANALY_IN2P3-CC_CL7", 
          "state_update": "2018-04-09T22:30:37.830032", 
          "status": "production", 
          "type": "CE"
        }, 
        {
          "endpoint": "cccreamceli01.in2p3.fr:8443", 
          "flavour": "CREAM-CE", 
          "id": 2822, 
          "last_modified": "2018-06-04T11:32:01.920263", 
          "name": "IN2P3-CC-CE-TEST-cccreamceli01.in2p3.fr", 
          "site": "IN2P3-CC", 
          "state": "ACTIVE", 
          "state_comment": "Auto ENABLED since the queue=long is attached to the PandaQueue IN2P3-CC_CL7", 
          "state_update": "2018-06-04T11:32:01.920212", 
          "status": "production", 
          "type": "CE"
        }, 
        {
          "endpoint": "cccreamceli04.in2p3.fr:8443", 
          "flavour": "CREAM-CE", 
          "id": 14263, 
          "last_modified": "2018-03-21T20:59:12.971140", 
          "name": "IN2P3-CC-CE-cccreamceli04.in2p3.fr", 
          "site": "IN2P3-CC", 
          "state": "ACTIVE", 
          "state_comment": "Auto ENABLED since the queue=long is attached to the PandaQueue IN2P3-CC_CL7", 
          "state_update": "2018-03-21T20:59:12.971045", 
          "status": "production", 
          "type": "CE"
        }, 
        {
          "endpoint": "cccreamceli03.in2p3.fr:8443", 
          "flavour": "CREAM-CE", 
          "id": 17536, 
          "last_modified": "2016-06-01T10:22:14.710032", 
          "name": "IN2P3-CC-CE-cccreamceli03.in2p3.fr", 
          "site": "IN2P3-CC", 
          "state": "ACTIVE", 
          "state_comment": "Auto ENABLED since the queue=mc_long is attached to the PandaQueue IN2P3-CC_MCORE", 
          "state_update": "2016-06-01T10:22:14.709941", 
          "status": "production", 
          "type": "CE"
        }, 
        {
          "endpoint": "ccperfsonar1.in2p3.fr", 
          "flavour": "Bandwidth", 
          "id": 14404, 
          "last_modified": "2015-01-29T17:01:37.285208", 
          "name": "IN2P3-CC-PerfSonar-Bandwidth-ccperfsonar1.in2p3.fr", 
          "site": "IN2P3-CC", 
          "state": "ACTIVE", 
          "state_comment": "automatically collected from GOCDB/OIM source (ACTIVE by default)", 
          "state_update": "2014-03-25T18:01:28.965152", 
          "status": "production", 
          "type": "PerfSonar"
        }, 
        {
          "endpoint": "ccperfsonar2.in2p3.fr", 
          "flavour": "Latency", 
          "id": 14405, 
          "last_modified": "2015-01-29T17:01:37.839072", 
          "name": "IN2P3-CC-PerfSonar-Latency-ccperfsonar2.in2p3.fr", 
          "site": "IN2P3-CC", 
          "state": "ACTIVE", 
          "state_comment": "automatically collected from GOCDB/OIM source (ACTIVE by default)", 
          "state_update": "2014-03-25T18:01:29.068389", 
          "status": "production", 
          "type": "PerfSonar"
        }, 
        {
          "endpoint": "srm://ccsrm.in2p3.fr:8443/srm/managerv2?SFN=", 
          "flavour": "SRM", 
          "id": 2394, 
          "last_modified": "2015-01-29T17:01:29.169832", 
          "name": "IN2P3-CC-SRM-ccsrm.in2p3.fr", 
          "site": "IN2P3-CC", 
          "state": "ACTIVE", 
          "state_comment": "", 
          "state_update": null, 
          "status": "production", 
          "type": "SRM"
        }
      ], 
      "severity": "OUTAGE", 
      "site": "IN2P3-CC", 
      "site_id": 1256, 
      "start_time": "2019-03-12T06:00:00", 
      "state": "ACTIVE"
    }, 
    {
      "affected_services": "CREAM-CE, CUSTOM.ch.cern.frontier.FroNTier, Central-LFC, SRM, SRM.nearline, Site-BDII, Top-BDII, VOMS, XRootD.Redirector, emi.ARGUS, eu.egi.storage.accounting, gLExec, gLite-APEL, net.perfSONAR.Bandwidth, net.perfSONAR.Latency, ngi.SAM, org.squid-cache.Squid", 
      "classification": "SCHEDULED", 
      "create_time": "2018-07-03T13:53:48", 
      "description": "Scheduled site maintenance. More details during the month before the outage ", 
      "end_time": "2019-06-11T23:00:00", 
      "id": 124382, 
      "info_url": "https://goc.egi.eu/portal/index.php?Page_Type=Downtime&id=25579", 
      "is_published": false, 
      "last_modified": "2018-07-03T16:00:26.638071", 
      "last_published": null, 
      "pid": "104191G0", 
      "provider": "GOCDB", 
      "rc_site": "IN2P3-CC", 
      "services": [
        {
          "endpoint": "cccreamceli05.in2p3.fr:8443", 
          "flavour": "CREAM-CE", 
          "id": 2620, 
          "last_modified": "2018-04-09T22:30:37.830087", 
          "name": "IN2P3-CC-CE-cccreamceli05.in2p3.fr", 
          "site": "IN2P3-CC", 
          "state": "ACTIVE", 
          "state_comment": "Auto ENABLED since the queue=long is attached to the PandaQueue ANALY_IN2P3-CC_CL7", 
          "state_update": "2018-04-09T22:30:37.830032", 
          "status": "production", 
          "type": "CE"
        }, 
        {
          "endpoint": "cccreamceli01.in2p3.fr:8443", 
          "flavour": "CREAM-CE", 
          "id": 2822, 
          "last_modified": "2018-06-04T11:32:01.920263", 
          "name": "IN2P3-CC-CE-TEST-cccreamceli01.in2p3.fr", 
          "site": "IN2P3-CC", 
          "state": "ACTIVE", 
          "state_comment": "Auto ENABLED since the queue=long is attached to the PandaQueue IN2P3-CC_CL7", 
          "state_update": "2018-06-04T11:32:01.920212", 
          "status": "production", 
          "type": "CE"
        }, 
        {
          "endpoint": "cccreamceli04.in2p3.fr:8443", 
          "flavour": "CREAM-CE", 
          "id": 14263, 
          "last_modified": "2018-03-21T20:59:12.971140", 
          "name": "IN2P3-CC-CE-cccreamceli04.in2p3.fr", 
          "site": "IN2P3-CC", 
          "state": "ACTIVE", 
          "state_comment": "Auto ENABLED since the queue=long is attached to the PandaQueue IN2P3-CC_CL7", 
          "state_update": "2018-03-21T20:59:12.971045", 
          "status": "production", 
          "type": "CE"
        }, 
        {
          "endpoint": "cccreamceli03.in2p3.fr:8443", 
          "flavour": "CREAM-CE", 
          "id": 17536, 
          "last_modified": "2016-06-01T10:22:14.710032", 
          "name": "IN2P3-CC-CE-cccreamceli03.in2p3.fr", 
          "site": "IN2P3-CC", 
          "state": "ACTIVE", 
          "state_comment": "Auto ENABLED since the queue=mc_long is attached to the PandaQueue IN2P3-CC_MCORE", 
          "state_update": "2016-06-01T10:22:14.709941", 
          "status": "production", 
          "type": "CE"
        }, 
        {
          "endpoint": "http://ccfrontier.in2p3.fr:23128/ccin2p3-AtlasFrontier", 
          "flavour": "", 
          "id": 2453, 
          "last_modified": "2012-02-21T11:02:10.101169", 
          "name": "IN2P3-CC-Frontier", 
          "site": "IN2P3-CC", 
          "state": "ACTIVE", 
          "state_comment": "", 
          "state_update": null, 
          "status": "", 
          "type": "Frontier"
        }, 
        {
          "endpoint": "ccperfsonar1.in2p3.fr", 
          "flavour": "Bandwidth", 
          "id": 14404, 
          "last_modified": "2015-01-29T17:01:37.285208", 
          "name": "IN2P3-CC-PerfSonar-Bandwidth-ccperfsonar1.in2p3.fr", 
          "site": "IN2P3-CC", 
          "state": "ACTIVE", 
          "state_comment": "automatically collected from GOCDB/OIM source (ACTIVE by default)", 
          "state_update": "2014-03-25T18:01:28.965152", 
          "status": "production", 
          "type": "PerfSonar"
        }, 
        {
          "endpoint": "ccperfsonar2.in2p3.fr", 
          "flavour": "Latency", 
          "id": 14405, 
          "last_modified": "2015-01-29T17:01:37.839072", 
          "name": "IN2P3-CC-PerfSonar-Latency-ccperfsonar2.in2p3.fr", 
          "site": "IN2P3-CC", 
          "state": "ACTIVE", 
          "state_comment": "automatically collected from GOCDB/OIM source (ACTIVE by default)", 
          "state_update": "2014-03-25T18:01:29.068389", 
          "status": "production", 
          "type": "PerfSonar"
        }, 
        {
          "endpoint": "srm://ccsrm.in2p3.fr:8443/srm/managerv2?SFN=", 
          "flavour": "SRM", 
          "id": 2394, 
          "last_modified": "2015-01-29T17:01:29.169832", 
          "name": "IN2P3-CC-SRM-ccsrm.in2p3.fr", 
          "site": "IN2P3-CC", 
          "state": "ACTIVE", 
          "state_comment": "", 
          "state_update": null, 
          "status": "production", 
          "type": "SRM"
        }
      ], 
      "severity": "OUTAGE", 
      "site": "IN2P3-CC", 
      "site_id": 1256, 
      "start_time": "2019-06-11T05:00:00", 
      "state": "ACTIVE"
    }
  ], 
  "IN2P3-CC-T3": [
    {
      "affected_services": "CREAM-CE, Central-LFC, SRM, SRM.nearline, Site-BDII, Top-BDII, VOMS, XRootD.Redirector, emi.ARGUS, gLExec, gLite-APEL, net.perfSONAR.Bandwidth, net.perfSONAR.Latency, ngi.SAM, org.squid-cache.Squid", 
      "classification": "SCHEDULED", 
      "create_time": "2017-09-20T13:03:50", 
      "description": "Scheduled site maintenance. More details during the month before the outage.", 
      "end_time": "2018-09-18T23:00:00", 
      "id": 123288, 
      "info_url": "https://goc.egi.eu/portal/index.php?Page_Type=Downtime&id=24010", 
      "is_published": false, 
      "last_modified": "2017-09-20T15:15:05.765105", 
      "last_published": null, 
      "pid": "102601G0", 
      "provider": "GOCDB", 
      "rc_site": "IN2P3-CC", 
      "services": [
        {
          "endpoint": "ccperfsonar1.in2p3.fr", 
          "flavour": "Bandwidth", 
          "id": 14404, 
          "last_modified": "2015-01-29T17:01:37.285208", 
          "name": "IN2P3-CC-PerfSonar-Bandwidth-ccperfsonar1.in2p3.fr", 
          "site": "IN2P3-CC", 
          "state": "ACTIVE", 
          "state_comment": "automatically collected from GOCDB/OIM source (ACTIVE by default)", 
          "state_update": "2014-03-25T18:01:28.965152", 
          "status": "production", 
          "type": "PerfSonar"
        }, 
        {
          "endpoint": "ccperfsonar2.in2p3.fr", 
          "flavour": "Latency", 
          "id": 14405, 
          "last_modified": "2015-01-29T17:01:37.839072", 
          "name": "IN2P3-CC-PerfSonar-Latency-ccperfsonar2.in2p3.fr", 
          "site": "IN2P3-CC", 
          "state": "ACTIVE", 
          "state_comment": "automatically collected from GOCDB/OIM source (ACTIVE by default)", 
          "state_update": "2014-03-25T18:01:29.068389", 
          "status": "production", 
          "type": "PerfSonar"
        }
      ], 
      "severity": "OUTAGE", 
      "site": "IN2P3-CC", 
      "site_id": 1256, 
      "start_time": "2018-09-18T05:00:00", 
      "state": "ACTIVE"
    }, 
    {
      "affected_services": "CREAM-CE, Central-LFC, SRM, SRM.nearline, Site-BDII, Top-BDII, VOMS, XRootD.Redirector, emi.ARGUS, eu.egi.storage.accounting, gLExec, gLite-APEL, net.perfSONAR.Bandwidth, net.perfSONAR.Latency, ngi.SAM, org.squid-cache.Squid", 
      "classification": "SCHEDULED", 
      "create_time": "2017-12-06T10:21:38", 
      "description": "Scheduled site maintenance. More details during the month before the outage", 
      "end_time": "2018-12-04T21:00:00", 
      "id": 123571, 
      "info_url": "https://goc.egi.eu/portal/index.php?Page_Type=Downtime&id=24460", 
      "is_published": false, 
      "last_modified": "2017-12-06T11:30:06.268550", 
      "last_published": null, 
      "pid": "103051G0", 
      "provider": "GOCDB", 
      "rc_site": "IN2P3-CC", 
      "services": [
        {
          "endpoint": "ccperfsonar1.in2p3.fr", 
          "flavour": "Bandwidth", 
          "id": 14404, 
          "last_modified": "2015-01-29T17:01:37.285208", 
          "name": "IN2P3-CC-PerfSonar-Bandwidth-ccperfsonar1.in2p3.fr", 
          "site": "IN2P3-CC", 
          "state": "ACTIVE", 
          "state_comment": "automatically collected from GOCDB/OIM source (ACTIVE by default)", 
          "state_update": "2014-03-25T18:01:28.965152", 
          "status": "production", 
          "type": "PerfSonar"
        }, 
        {
          "endpoint": "ccperfsonar2.in2p3.fr", 
          "flavour": "Latency", 
          "id": 14405, 
          "last_modified": "2015-01-29T17:01:37.839072", 
          "name": "IN2P3-CC-PerfSonar-Latency-ccperfsonar2.in2p3.fr", 
          "site": "IN2P3-CC", 
          "state": "ACTIVE", 
          "state_comment": "automatically collected from GOCDB/OIM source (ACTIVE by default)", 
          "state_update": "2014-03-25T18:01:29.068389", 
          "status": "production", 
          "type": "PerfSonar"
        }
      ], 
      "severity": "OUTAGE", 
      "site": "IN2P3-CC", 
      "site_id": 1256, 
      "start_time": "2018-12-04T07:00:00", 
      "state": "ACTIVE"
    }, 
    {
      "affected_services": "CREAM-CE, Central-LFC, SRM, SRM.nearline, Site-BDII, Top-BDII, VOMS, XRootD.Redirector, emi.ARGUS, eu.egi.storage.accounting, gLExec, gLite-APEL, net.perfSONAR.Bandwidth, net.perfSONAR.Latency, ngi.SAM, org.squid-cache.Squid", 
      "classification": "SCHEDULED", 
      "create_time": "2018-03-19T10:15:54", 
      "description": "Scheduled site maintenance. More details during the month before the outage.", 
      "end_time": "2019-03-12T23:00:00", 
      "id": 123974, 
      "info_url": "https://goc.egi.eu/portal/index.php?Page_Type=Downtime&id=25059", 
      "is_published": false, 
      "last_modified": "2018-03-19T11:30:05.778952", 
      "last_published": null, 
      "pid": "103671G0", 
      "provider": "GOCDB", 
      "rc_site": "IN2P3-CC", 
      "services": [
        {
          "endpoint": "ccperfsonar1.in2p3.fr", 
          "flavour": "Bandwidth", 
          "id": 14404, 
          "last_modified": "2015-01-29T17:01:37.285208", 
          "name": "IN2P3-CC-PerfSonar-Bandwidth-ccperfsonar1.in2p3.fr", 
          "site": "IN2P3-CC", 
          "state": "ACTIVE", 
          "state_comment": "automatically collected from GOCDB/OIM source (ACTIVE by default)", 
          "state_update": "2014-03-25T18:01:28.965152", 
          "status": "production", 
          "type": "PerfSonar"
        }, 
        {
          "endpoint": "ccperfsonar2.in2p3.fr", 
          "flavour": "Latency", 
          "id": 14405, 
          "last_modified": "2015-01-29T17:01:37.839072", 
          "name": "IN2P3-CC-PerfSonar-Latency-ccperfsonar2.in2p3.fr", 
          "site": "IN2P3-CC", 
          "state": "ACTIVE", 
          "state_comment": "automatically collected from GOCDB/OIM source (ACTIVE by default)", 
          "state_update": "2014-03-25T18:01:29.068389", 
          "status": "production", 
          "type": "PerfSonar"
        }
      ], 
      "severity": "OUTAGE", 
      "site": "IN2P3-CC", 
      "site_id": 1256, 
      "start_time": "2019-03-12T06:00:00", 
      "state": "ACTIVE"
    }, 
    {
      "affected_services": "CREAM-CE, CUSTOM.ch.cern.frontier.FroNTier, Central-LFC, SRM, SRM.nearline, Site-BDII, Top-BDII, VOMS, XRootD.Redirector, emi.ARGUS, eu.egi.storage.accounting, gLExec, gLite-APEL, net.perfSONAR.Bandwidth, net.perfSONAR.Latency, ngi.SAM, org.squid-cache.Squid", 
      "classification": "SCHEDULED", 
      "create_time": "2018-07-03T13:53:48", 
      "description": "Scheduled site maintenance. More details during the month before the outage ", 
      "end_time": "2019-06-11T23:00:00", 
      "id": 124382, 
      "info_url": "https://goc.egi.eu/portal/index.php?Page_Type=Downtime&id=25579", 
      "is_published": false, 
      "last_modified": "2018-07-03T16:00:26.638071", 
      "last_published": null, 
      "pid": "104191G0", 
      "provider": "GOCDB", 
      "rc_site": "IN2P3-CC", 
      "services": [
        {
          "endpoint": "http://ccfrontier.in2p3.fr:23128/ccin2p3-AtlasFrontier", 
          "flavour": "", 
          "id": 2453, 
          "last_modified": "2012-02-21T11:02:10.101169", 
          "name": "IN2P3-CC-Frontier", 
          "site": "IN2P3-CC", 
          "state": "ACTIVE", 
          "state_comment": "", 
          "state_update": null, 
          "status": "", 
          "type": "Frontier"
        }, 
        {
          "endpoint": "ccperfsonar1.in2p3.fr", 
          "flavour": "Bandwidth", 
          "id": 14404, 
          "last_modified": "2015-01-29T17:01:37.285208", 
          "name": "IN2P3-CC-PerfSonar-Bandwidth-ccperfsonar1.in2p3.fr", 
          "site": "IN2P3-CC", 
          "state": "ACTIVE", 
          "state_comment": "automatically collected from GOCDB/OIM source (ACTIVE by default)", 
          "state_update": "2014-03-25T18:01:28.965152", 
          "status": "production", 
          "type": "PerfSonar"
        }, 
        {
          "endpoint": "ccperfsonar2.in2p3.fr", 
          "flavour": "Latency", 
          "id": 14405, 
          "last_modified": "2015-01-29T17:01:37.839072", 
          "name": "IN2P3-CC-PerfSonar-Latency-ccperfsonar2.in2p3.fr", 
          "site": "IN2P3-CC", 
          "state": "ACTIVE", 
          "state_comment": "automatically collected from GOCDB/OIM source (ACTIVE by default)", 
          "state_update": "2014-03-25T18:01:29.068389", 
          "status": "production", 
          "type": "PerfSonar"
        }
      ], 
      "severity": "OUTAGE", 
      "site": "IN2P3-CC", 
      "site_id": 1256, 
      "start_time": "2019-06-11T05:00:00", 
      "state": "ACTIVE"
    }
  ], 
  "INFN-BOLOGNA-T3": [
    {
      "affected_services": "APEL, CREAM-CE, gLExec", 
      "classification": "UNSCHEDULED", 
      "create_time": "2018-05-28T07:36:04", 
      "description": " Service Not Available ", 
      "end_time": "2019-01-31T23:00:00", 
      "id": 124249, 
      "info_url": "https://goc.egi.eu/portal/index.php?Page_Type=Downtime&id=25393", 
      "is_published": false, 
      "last_modified": "2018-05-28T09:45:05.384191", 
      "last_published": null, 
      "pid": "104005G0", 
      "provider": "GOCDB", 
      "rc_site": "INFN-BOLOGNA-T3", 
      "services": [
        {
          "endpoint": "cebo-t3-01.cr.cnaf.infn.it:8443", 
          "flavour": "CREAM-CE", 
          "id": 2814, 
          "last_modified": "2018-07-16T12:32:16.950467", 
          "name": "INFN-BOLOGNA-T3-CE-cebo-t3-01.cr.cnaf.infn.it", 
          "site": "INFN-BOLOGNA-T3", 
          "state": "ACTIVE", 
          "state_comment": "", 
          "state_update": null, 
          "status": "DISABLED", 
          "type": "CE"
        }
      ], 
      "severity": "OUTAGE", 
      "site": "INFN-BOLOGNA-T3", 
      "site_id": 1228, 
      "start_time": "2018-05-28T09:00:00", 
      "state": "ACTIVE"
    }, 
    {
      "affected_services": "APEL, CREAM-CE, SRM, Site-BDII, emi.ARGUS, gLExec", 
      "classification": "SCHEDULED", 
      "create_time": "2018-07-02T10:08:04", 
      "description": "Decommissioning  INFN-BOLOGNA-T3", 
      "end_time": "2018-12-30T22:00:00", 
      "id": 124375, 
      "info_url": "https://goc.egi.eu/portal/index.php?Page_Type=Downtime&id=25569", 
      "is_published": false, 
      "last_modified": "2018-07-02T12:15:07.001105", 
      "last_published": null, 
      "pid": "104181G0", 
      "provider": "GOCDB", 
      "rc_site": "INFN-BOLOGNA-T3", 
      "services": [
        {
          "endpoint": "cebo-t3-01.cr.cnaf.infn.it:8443", 
          "flavour": "CREAM-CE", 
          "id": 2814, 
          "last_modified": "2018-07-16T12:32:16.950467", 
          "name": "INFN-BOLOGNA-T3-CE-cebo-t3-01.cr.cnaf.infn.it", 
          "site": "INFN-BOLOGNA-T3", 
          "state": "ACTIVE", 
          "state_comment": "", 
          "state_update": null, 
          "status": "DISABLED", 
          "type": "CE"
        }, 
        {
          "endpoint": "srm://sebo-t3-01.cr.cnaf.infn.it:8444/srm/managerv2?SFN=", 
          "flavour": "SRM", 
          "id": 2410, 
          "last_modified": "2018-07-16T12:32:16.921588", 
          "name": "INFN-BOLOGNA-T3-SRM-sebo-t3-01.cr.cnaf.infn.it", 
          "site": "INFN-BOLOGNA-T3", 
          "state": "ACTIVE", 
          "state_comment": "", 
          "state_update": null, 
          "status": "DISABLED", 
          "type": "SRM"
        }
      ], 
      "severity": "OUTAGE", 
      "site": "INFN-BOLOGNA-T3", 
      "site_id": 1228, 
      "start_time": "2018-07-03T12:00:00", 
      "state": "ACTIVE"
    }
  ], 
  "NDGF-T1": [
    {
      "affected_services": "ARC-CE", 
      "classification": "SCHEDULED", 
      "create_time": "2018-07-26T14:49:20", 
      "description": "CE down for complete rebuild and physical relocation. ", 
      "end_time": "2018-12-31T15:00:00", 
      "id": 124454, 
      "info_url": "https://goc.egi.eu/portal/index.php?Page_Type=Downtime&id=25743", 
      "is_published": false, 
      "last_modified": "2018-07-26T17:00:12.722141", 
      "last_published": null, 
      "pid": "104356G0", 
      "provider": "GOCDB", 
      "rc_site": "NDGF-T1", 
      "services": [
        {
          "endpoint": "gsiftp://atlas.triolith.nsc.liu.se:2811", 
          "flavour": "ARC-CE", 
          "id": 14302, 
          "last_modified": "2018-07-16T18:32:13.851931", 
          "name": "NDGF-T1-CE-atlas.triolith.nsc.liu.se", 
          "site": "NDGF-T1", 
          "state": "ACTIVE", 
          "state_comment": "automatically collected from GOCDB/OIM source", 
          "state_update": "2014-05-17T07:54:55.660003", 
          "status": "DISABLED", 
          "type": "CE"
        }
      ], 
      "severity": "OUTAGE", 
      "site": "NDGF-T1", 
      "site_id": 1176, 
      "start_time": "2018-07-27T15:00:00", 
      "state": "ACTIVE"
    }, 
    {
      "affected_services": "ARC-CE", 
      "classification": "SCHEDULED", 
      "create_time": "2018-08-13T13:36:45", 
      "description": "Infiniband maintenance", 
      "end_time": "2018-09-10T23:59:00", 
      "id": 124540, 
      "info_url": "https://goc.egi.eu/portal/index.php?Page_Type=Downtime&id=25867", 
      "is_published": false, 
      "last_modified": "2018-08-13T15:45:07.192880", 
      "last_published": null, 
      "pid": "104480G0", 
      "provider": "GOCDB", 
      "rc_site": "NDGF-T1", 
      "services": [
        {
          "endpoint": "gsiftp://ce01.grid.uio.no:2811", 
          "flavour": "ARC-CE", 
          "id": 8522, 
          "last_modified": "2015-06-15T10:20:03.914315", 
          "name": "NDGF-T1-CE-ce01.grid.uio.no", 
          "site": "NDGF-T1", 
          "state": "ACTIVE", 
          "state_comment": "automatically collected from GOCDB/OIM sources", 
          "state_update": "2014-05-15T14:24:38.595177", 
          "status": "production", 
          "type": "CE"
        }
      ], 
      "severity": "OUTAGE", 
      "site": "NDGF-T1", 
      "site_id": 1176, 
      "start_time": "2018-09-10T00:00:00", 
      "state": "ACTIVE"
    }
  ], 
  "RO-16-UAIC": [
    {
      "affected_services": "APEL, ARC-CE, CREAM-CE, Site-BDII, UI, gLExec, gLite-APEL, net.perfSONAR.Bandwidth, net.perfSONAR.Latency, org.squid-cache.Squid", 
      "classification": "SCHEDULED", 
      "create_time": "2018-08-31T15:43:10", 
      "description": "lack of financing for RO-16-UAIC", 
      "end_time": "2018-09-29T21:00:00", 
      "id": 124587, 
      "info_url": "https://goc.egi.eu/portal/index.php?Page_Type=Downtime&id=25982", 
      "is_published": false, 
      "last_modified": "2018-08-31T17:45:07.508579", 
      "last_published": null, 
      "pid": "104595G0", 
      "provider": "GOCDB", 
      "rc_site": "RO-16-UAIC", 
      "services": [
        {
          "endpoint": "arc-grid.uaic.ro:2811", 
          "flavour": "ARC-CE", 
          "id": 18206, 
          "last_modified": "2018-04-02T14:38:46.256003", 
          "name": "RO-16-UAIC-CE-arc-grid.uaic.ro", 
          "site": "RO-16-UAIC", 
          "state": "ACTIVE", 
          "state_comment": "Auto ENABLED since the queue=debug is attached to the PandaQueue RO-16-UAIC-cream-grid-atlas-lcgpbs_ARC", 
          "state_update": "2018-04-02T14:38:46.255939", 
          "status": "production", 
          "type": "CE"
        }, 
        {
          "endpoint": "ce-grid.grid.uaic.ro:8443", 
          "flavour": "CREAM-CE", 
          "id": 2826, 
          "last_modified": "2015-01-29T17:01:35.204064", 
          "name": "RO-16-UAIC-CE-ce-grid.grid.uaic.ro", 
          "site": "RO-16-UAIC", 
          "state": "ACTIVE", 
          "state_comment": "", 
          "state_update": null, 
          "status": "production", 
          "type": "CE"
        }, 
        {
          "endpoint": "perfsonar-grid.uaic.ro", 
          "flavour": "Bandwidth", 
          "id": 7761, 
          "last_modified": "2015-01-29T17:01:37.447540", 
          "name": "RO-16-UAIC-PerfSonar-perfsonar-grid.uaic.ro", 
          "site": "RO-16-UAIC", 
          "state": "ACTIVE", 
          "state_comment": "automatically collected from GOCDB/OIM sources", 
          "state_update": "2013-02-14T18:01:42.362138", 
          "status": "production", 
          "type": "PerfSonar"
        }, 
        {
          "endpoint": "perfsonar2-grid.uaic.ro", 
          "flavour": "Latency", 
          "id": 7792, 
          "last_modified": "2015-01-29T17:01:37.227552", 
          "name": "RO-16-UAIC-PerfSonar-perfsonar2-grid.uaic.ro", 
          "site": "RO-16-UAIC", 
          "state": "ACTIVE", 
          "state_comment": "automatically collected from GOCDB/OIM sources", 
          "state_update": "2013-02-14T18:01:42.866057", 
          "status": "production", 
          "type": "PerfSonar"
        }, 
        {
          "endpoint": "http://squid-grid.uaic.ro:3128", 
          "flavour": "", 
          "id": 2488, 
          "last_modified": "2012-02-21T11:02:13.073704", 
          "name": "RO-16-UAIC-Squid", 
          "site": "RO-16-UAIC", 
          "state": "ACTIVE", 
          "state_comment": "", 
          "state_update": null, 
          "status": "", 
          "type": "Squid"
        }
      ], 
      "severity": "OUTAGE", 
      "site": "RO-16-UAIC", 
      "site_id": 1294, 
      "start_time": "2018-09-01T21:00:00", 
      "state": "ACTIVE"
    }
  ], 
  "SARA-MATRIX": [
    {
      "affected_services": "APEL, CREAM-CE, Central-LFC, LB, Local-LFC, MyProxy, SRM, SRM.nearline, Site-BDII, Top-BDII, UI, VO-box, VOMS, WMS, eu.egi.MPI, eu.egi.storage.accounting, gLExec, gLite-APEL, net.perfSONAR.Bandwidth, net.perfSONAR.Latency, ngi.ARGUS, ngi.SAM, org.squid-cache.Squid, webdav", 
      "classification": "SCHEDULED", 
      "create_time": "2018-08-21T15:34:33", 
      "description": "maintenance on SURFsara core network infrastructure", 
      "end_time": "2018-09-04T13:00:00", 
      "id": 124562, 
      "info_url": "https://goc.egi.eu/portal/index.php?Page_Type=Downtime&id=25896", 
      "is_published": false, 
      "last_modified": "2018-08-21T17:45:07.298192", 
      "last_published": null, 
      "pid": "104509G0", 
      "provider": "GOCDB", 
      "rc_site": "SARA-MATRIX", 
      "services": [
        {
          "endpoint": "creamce2.gina.sara.nl:8443", 
          "flavour": "CREAM-CE", 
          "id": 2549, 
          "last_modified": "2015-01-29T17:01:32.872963", 
          "name": "SARA-MATRIX-CE-creamce2.gina.sara.nl", 
          "site": "SARA-MATRIX", 
          "state": "ACTIVE", 
          "state_comment": "", 
          "state_update": null, 
          "status": "production", 
          "type": "CE"
        }, 
        {
          "endpoint": "creamce.gina.sara.nl:8443", 
          "flavour": "CREAM-CE", 
          "id": 2717, 
          "last_modified": "2015-01-29T17:01:36.108244", 
          "name": "SARA-MATRIX-CE-creamce.gina.sara.nl", 
          "site": "SARA-MATRIX", 
          "state": "ACTIVE", 
          "state_comment": "", 
          "state_update": "2014-10-10T10:54:50.910473", 
          "status": "production", 
          "type": "CE"
        }, 
        {
          "endpoint": "creamce3.gina.sara.nl:8443", 
          "flavour": "CREAM-CE", 
          "id": 6961, 
          "last_modified": "2015-01-29T17:01:36.388244", 
          "name": "SARA-MATRIX-CE-creamce3.gina.sara.nl", 
          "site": "SARA-MATRIX", 
          "state": "ACTIVE", 
          "state_comment": "automatically collected from GOCDB/OIM sources", 
          "state_update": "2013-05-13T16:45:31.149869", 
          "status": "production", 
          "type": "CE"
        }, 
        {
          "endpoint": "ps.lhcopn-ps.surfsara.nl", 
          "flavour": "Bandwidth", 
          "id": 17615, 
          "last_modified": "2016-06-07T18:02:13.327340", 
          "name": "SARA-MATRIX-PerfSonar-Bandwidth-ps.lhcopn-ps.surfsara.nl", 
          "site": "SARA-MATRIX", 
          "state": "ACTIVE", 
          "state_comment": "automatically collected from GOCDB/OIM source (ACTIVE by default)", 
          "state_update": "2016-06-07T18:02:13", 
          "status": "production", 
          "type": "PerfSonar"
        }, 
        {
          "endpoint": "ps2.lhcopn-ps.surfsara.nl", 
          "flavour": "Latency", 
          "id": 17616, 
          "last_modified": "2016-06-07T18:02:13.461404", 
          "name": "SARA-MATRIX-PerfSonar-Latency-ps2.lhcopn-ps.surfsara.nl", 
          "site": "SARA-MATRIX", 
          "state": "ACTIVE", 
          "state_comment": "automatically collected from GOCDB/OIM source (ACTIVE by default)", 
          "state_update": "2016-06-07T18:02:13", 
          "status": "production", 
          "type": "PerfSonar"
        }, 
        {
          "endpoint": "srm://srm.grid.sara.nl:8443/srm/managerv2?SFN=", 
          "flavour": "SRM", 
          "id": 2317, 
          "last_modified": "2015-01-29T17:01:27.772779", 
          "name": "SARA-MATRIX-SRM-srm.grid.sara.nl", 
          "site": "SARA-MATRIX", 
          "state": "ACTIVE", 
          "state_comment": "", 
          "state_update": null, 
          "status": "production", 
          "type": "SRM"
        }, 
        {
          "endpoint": "http://squid.grid.sara.nl:3128", 
          "flavour": "", 
          "id": 2532, 
          "last_modified": "2012-02-21T11:02:16.170639", 
          "name": "SARA-MATRIX-Squid", 
          "site": "SARA-MATRIX", 
          "state": "ACTIVE", 
          "state_comment": "", 
          "state_update": null, 
          "status": "", 
          "type": "Squid"
        }
      ], 
      "severity": "WARNING", 
      "site": "SARA-MATRIX", 
      "site_id": 1288, 
      "start_time": "2018-09-04T04:30:00", 
      "state": "ACTIVE"
    }, 
    {
      "affected_services": "SRM, SRM.nearline, webdav", 
      "classification": "UNSCHEDULED", 
      "create_time": "2018-09-03T10:28:52", 
      "description": "Upgrading one dCache pool node to test a bug fix. Some files may be unavailable for a few minutes. - OZ", 
      "end_time": "2018-09-04T09:00:00", 
      "id": 124591, 
      "info_url": "https://goc.egi.eu/portal/index.php?Page_Type=Downtime&id=25987", 
      "is_published": false, 
      "last_modified": "2018-09-03T12:30:07.086827", 
      "last_published": null, 
      "pid": "104600G0", 
      "provider": "GOCDB", 
      "rc_site": "SARA-MATRIX", 
      "services": [
        {
          "endpoint": "srm://srm.grid.sara.nl:8443/srm/managerv2?SFN=", 
          "flavour": "SRM", 
          "id": 2317, 
          "last_modified": "2015-01-29T17:01:27.772779", 
          "name": "SARA-MATRIX-SRM-srm.grid.sara.nl", 
          "site": "SARA-MATRIX", 
          "state": "ACTIVE", 
          "state_comment": "", 
          "state_update": null, 
          "status": "production", 
          "type": "SRM"
        }
      ], 
      "severity": "WARNING", 
      "site": "SARA-MATRIX", 
      "site_id": 1288, 
      "start_time": "2018-09-04T08:00:00", 
      "state": "ACTIVE"
    }
  ], 
  "T1_FR_CCIN2P3": [
    {
      "affected_services": "CREAM-CE, Central-LFC, SRM, SRM.nearline, Site-BDII, Top-BDII, VOMS, XRootD.Redirector, emi.ARGUS, gLExec, gLite-APEL, net.perfSONAR.Bandwidth, net.perfSONAR.Latency, ngi.SAM, org.squid-cache.Squid", 
      "classification": "SCHEDULED", 
      "create_time": "2017-09-20T13:03:50", 
      "description": "Scheduled site maintenance. More details during the month before the outage.", 
      "end_time": "2018-09-18T23:00:00", 
      "id": 123288, 
      "info_url": "https://goc.egi.eu/portal/index.php?Page_Type=Downtime&id=24010", 
      "is_published": false, 
      "last_modified": "2017-09-20T15:15:05.765105", 
      "last_published": null, 
      "pid": "102601G0", 
      "provider": "GOCDB", 
      "rc_site": "IN2P3-CC", 
      "services": [
        {
          "endpoint": "ccperfsonar1.in2p3.fr", 
          "flavour": "Bandwidth", 
          "id": 14404, 
          "last_modified": "2015-01-29T17:01:37.285208", 
          "name": "IN2P3-CC-PerfSonar-Bandwidth-ccperfsonar1.in2p3.fr", 
          "site": "IN2P3-CC", 
          "state": "ACTIVE", 
          "state_comment": "automatically collected from GOCDB/OIM source (ACTIVE by default)", 
          "state_update": "2014-03-25T18:01:28.965152", 
          "status": "production", 
          "type": "PerfSonar"
        }, 
        {
          "endpoint": "ccperfsonar2.in2p3.fr", 
          "flavour": "Latency", 
          "id": 14405, 
          "last_modified": "2015-01-29T17:01:37.839072", 
          "name": "IN2P3-CC-PerfSonar-Latency-ccperfsonar2.in2p3.fr", 
          "site": "IN2P3-CC", 
          "state": "ACTIVE", 
          "state_comment": "automatically collected from GOCDB/OIM source (ACTIVE by default)", 
          "state_update": "2014-03-25T18:01:29.068389", 
          "status": "production", 
          "type": "PerfSonar"
        }
      ], 
      "severity": "OUTAGE", 
      "site": "IN2P3-CC", 
      "site_id": 1256, 
      "start_time": "2018-09-18T05:00:00", 
      "state": "ACTIVE"
    }, 
    {
      "affected_services": "CREAM-CE, Central-LFC, SRM, SRM.nearline, Site-BDII, Top-BDII, VOMS, XRootD.Redirector, emi.ARGUS, eu.egi.storage.accounting, gLExec, gLite-APEL, net.perfSONAR.Bandwidth, net.perfSONAR.Latency, ngi.SAM, org.squid-cache.Squid", 
      "classification": "SCHEDULED", 
      "create_time": "2017-12-06T10:21:38", 
      "description": "Scheduled site maintenance. More details during the month before the outage", 
      "end_time": "2018-12-04T21:00:00", 
      "id": 123571, 
      "info_url": "https://goc.egi.eu/portal/index.php?Page_Type=Downtime&id=24460", 
      "is_published": false, 
      "last_modified": "2017-12-06T11:30:06.268550", 
      "last_published": null, 
      "pid": "103051G0", 
      "provider": "GOCDB", 
      "rc_site": "IN2P3-CC", 
      "services": [
        {
          "endpoint": "ccperfsonar1.in2p3.fr", 
          "flavour": "Bandwidth", 
          "id": 14404, 
          "last_modified": "2015-01-29T17:01:37.285208", 
          "name": "IN2P3-CC-PerfSonar-Bandwidth-ccperfsonar1.in2p3.fr", 
          "site": "IN2P3-CC", 
          "state": "ACTIVE", 
          "state_comment": "automatically collected from GOCDB/OIM source (ACTIVE by default)", 
          "state_update": "2014-03-25T18:01:28.965152", 
          "status": "production", 
          "type": "PerfSonar"
        }, 
        {
          "endpoint": "ccperfsonar2.in2p3.fr", 
          "flavour": "Latency", 
          "id": 14405, 
          "last_modified": "2015-01-29T17:01:37.839072", 
          "name": "IN2P3-CC-PerfSonar-Latency-ccperfsonar2.in2p3.fr", 
          "site": "IN2P3-CC", 
          "state": "ACTIVE", 
          "state_comment": "automatically collected from GOCDB/OIM source (ACTIVE by default)", 
          "state_update": "2014-03-25T18:01:29.068389", 
          "status": "production", 
          "type": "PerfSonar"
        }
      ], 
      "severity": "OUTAGE", 
      "site": "IN2P3-CC", 
      "site_id": 1256, 
      "start_time": "2018-12-04T07:00:00", 
      "state": "ACTIVE"
    }, 
    {
      "affected_services": "CREAM-CE, Central-LFC, SRM, SRM.nearline, Site-BDII, Top-BDII, VOMS, XRootD.Redirector, emi.ARGUS, eu.egi.storage.accounting, gLExec, gLite-APEL, net.perfSONAR.Bandwidth, net.perfSONAR.Latency, ngi.SAM, org.squid-cache.Squid", 
      "classification": "SCHEDULED", 
      "create_time": "2018-03-19T10:15:54", 
      "description": "Scheduled site maintenance. More details during the month before the outage.", 
      "end_time": "2019-03-12T23:00:00", 
      "id": 123974, 
      "info_url": "https://goc.egi.eu/portal/index.php?Page_Type=Downtime&id=25059", 
      "is_published": false, 
      "last_modified": "2018-03-19T11:30:05.778952", 
      "last_published": null, 
      "pid": "103671G0", 
      "provider": "GOCDB", 
      "rc_site": "IN2P3-CC", 
      "services": [
        {
          "endpoint": "ccperfsonar1.in2p3.fr", 
          "flavour": "Bandwidth", 
          "id": 14404, 
          "last_modified": "2015-01-29T17:01:37.285208", 
          "name": "IN2P3-CC-PerfSonar-Bandwidth-ccperfsonar1.in2p3.fr", 
          "site": "IN2P3-CC", 
          "state": "ACTIVE", 
          "state_comment": "automatically collected from GOCDB/OIM source (ACTIVE by default)", 
          "state_update": "2014-03-25T18:01:28.965152", 
          "status": "production", 
          "type": "PerfSonar"
        }, 
        {
          "endpoint": "ccperfsonar2.in2p3.fr", 
          "flavour": "Latency", 
          "id": 14405, 
          "last_modified": "2015-01-29T17:01:37.839072", 
          "name": "IN2P3-CC-PerfSonar-Latency-ccperfsonar2.in2p3.fr", 
          "site": "IN2P3-CC", 
          "state": "ACTIVE", 
          "state_comment": "automatically collected from GOCDB/OIM source (ACTIVE by default)", 
          "state_update": "2014-03-25T18:01:29.068389", 
          "status": "production", 
          "type": "PerfSonar"
        }
      ], 
      "severity": "OUTAGE", 
      "site": "IN2P3-CC", 
      "site_id": 1256, 
      "start_time": "2019-03-12T06:00:00", 
      "state": "ACTIVE"
    }, 
    {
      "affected_services": "CREAM-CE, CUSTOM.ch.cern.frontier.FroNTier, Central-LFC, SRM, SRM.nearline, Site-BDII, Top-BDII, VOMS, XRootD.Redirector, emi.ARGUS, eu.egi.storage.accounting, gLExec, gLite-APEL, net.perfSONAR.Bandwidth, net.perfSONAR.Latency, ngi.SAM, org.squid-cache.Squid", 
      "classification": "SCHEDULED", 
      "create_time": "2018-07-03T13:53:48", 
      "description": "Scheduled site maintenance. More details during the month before the outage ", 
      "end_time": "2019-06-11T23:00:00", 
      "id": 124382, 
      "info_url": "https://goc.egi.eu/portal/index.php?Page_Type=Downtime&id=25579", 
      "is_published": false, 
      "last_modified": "2018-07-03T16:00:26.638071", 
      "last_published": null, 
      "pid": "104191G0", 
      "provider": "GOCDB", 
      "rc_site": "IN2P3-CC", 
      "services": [
        {
          "endpoint": "http://ccfrontier.in2p3.fr:23128/ccin2p3-AtlasFrontier", 
          "flavour": "", 
          "id": 2453, 
          "last_modified": "2012-02-21T11:02:10.101169", 
          "name": "IN2P3-CC-Frontier", 
          "site": "IN2P3-CC", 
          "state": "ACTIVE", 
          "state_comment": "", 
          "state_update": null, 
          "status": "", 
          "type": "Frontier"
        }, 
        {
          "endpoint": "ccperfsonar1.in2p3.fr", 
          "flavour": "Bandwidth", 
          "id": 14404, 
          "last_modified": "2015-01-29T17:01:37.285208", 
          "name": "IN2P3-CC-PerfSonar-Bandwidth-ccperfsonar1.in2p3.fr", 
          "site": "IN2P3-CC", 
          "state": "ACTIVE", 
          "state_comment": "automatically collected from GOCDB/OIM source (ACTIVE by default)", 
          "state_update": "2014-03-25T18:01:28.965152", 
          "status": "production", 
          "type": "PerfSonar"
        }, 
        {
          "endpoint": "ccperfsonar2.in2p3.fr", 
          "flavour": "Latency", 
          "id": 14405, 
          "last_modified": "2015-01-29T17:01:37.839072", 
          "name": "IN2P3-CC-PerfSonar-Latency-ccperfsonar2.in2p3.fr", 
          "site": "IN2P3-CC", 
          "state": "ACTIVE", 
          "state_comment": "automatically collected from GOCDB/OIM source (ACTIVE by default)", 
          "state_update": "2014-03-25T18:01:29.068389", 
          "status": "production", 
          "type": "PerfSonar"
        }
      ], 
      "severity": "OUTAGE", 
      "site": "IN2P3-CC", 
      "site_id": 1256, 
      "start_time": "2019-06-11T05:00:00", 
      "state": "ACTIVE"
    }
  ], 
  "T2_AT_Vienna": [
    {
      "affected_services": "APEL, CREAM-CE, gLExec", 
      "classification": "SCHEDULED", 
      "create_time": "2018-09-01T14:48:29", 
      "description": "Finishing configuration", 
      "end_time": "2018-09-05T23:59:00", 
      "id": 124589, 
      "info_url": "https://goc.egi.eu/portal/index.php?Page_Type=Downtime&id=25985", 
      "is_published": false, 
      "last_modified": "2018-09-01T17:00:11.902769", 
      "last_published": null, 
      "pid": "104598G0", 
      "provider": "GOCDB", 
      "rc_site": "Hephy-Vienna", 
      "services": [], 
      "severity": "OUTAGE", 
      "site": "Hephy-Vienna", 
      "site_id": 1489, 
      "start_time": "2018-09-02T15:00:00", 
      "state": "ACTIVE"
    }
  ], 
  "T2_PL_Warsaw": [
    {
      "affected_services": "CREAM-CE, CUSTOM.pl.plgrid.BAT.agent, CUSTOM.pl.plgrid.KeyFS, CUSTOM_SERVICE, QCG.Computing, QCG.Notification, SRM, Site-BDII, Top-BDII, UI, WMS, com.schedmd.SlurmClient, emi.ARGUS, eu.egi.MPI, eu.egi.storage.accounting, gLExec, gLite-APEL, globus-GRIDFTP, org.squid-cache.Squid, unicore6.Gateway, unicore6.StorageManagement, unicore6.TargetSystemFactory", 
      "classification": "SCHEDULED", 
      "create_time": "2018-08-09T14:37:39", 
      "description": "energy supply problem", 
      "end_time": "2018-12-31T22:59:00", 
      "id": 124532, 
      "info_url": "https://goc.egi.eu/portal/index.php?Page_Type=Downtime&id=25849", 
      "is_published": false, 
      "last_modified": "2018-08-11T07:30:07.565964", 
      "last_published": null, 
      "pid": "104462G0", 
      "provider": "GOCDB", 
      "rc_site": "ICM", 
      "services": [], 
      "severity": "OUTAGE", 
      "site": "ICM", 
      "site_id": 2214, 
      "start_time": "2018-08-13T08:00:00", 
      "state": "ACTIVE"
    }
  ], 
  "UNI-FREIBURG": [
    {
      "affected_services": "net.perfSONAR.Bandwidth, net.perfSONAR.Latency", 
      "classification": "SCHEDULED", 
      "create_time": "2018-08-11T15:32:20", 
      "description": "PerfSonar migration to new HW and CentOS7", 
      "end_time": "2018-12-13T20:00:00", 
      "id": 124535, 
      "info_url": "https://goc.egi.eu/portal/index.php?Page_Type=Downtime&id=25862", 
      "is_published": false, 
      "last_modified": "2018-08-11T17:45:20.498806", 
      "last_published": null, 
      "pid": "104475G0", 
      "provider": "GOCDB", 
      "rc_site": "UNI-FREIBURG", 
      "services": [
        {
          "endpoint": "ps02.bfg.uni-freiburg.de", 
          "flavour": "Bandwidth", 
          "id": 14103, 
          "last_modified": "2016-04-22T06:02:04.387556", 
          "name": "UNI-FREIBURG-PerfSonar-Bandwidth-ps02.bfg.uni-freiburg.de", 
          "site": "UNI-FREIBURG", 
          "state": "ACTIVE", 
          "state_comment": "automatically collected from GOCDB/OIM source (ACTIVE by default)", 
          "state_update": "2014-03-06T00:01:26.616245", 
          "status": "production", 
          "type": "PerfSonar"
        }, 
        {
          "endpoint": "ps01.bfg.uni-freiburg.de", 
          "flavour": "Latency", 
          "id": 14102, 
          "last_modified": "2016-04-22T06:02:04.408820", 
          "name": "UNI-FREIBURG-PerfSonar-Latency-ps01.bfg.uni-freiburg.de", 
          "site": "UNI-FREIBURG", 
          "state": "ACTIVE", 
          "state_comment": "automatically collected from GOCDB/OIM source (ACTIVE by default)", 
          "state_update": "2014-03-06T00:01:26.500908", 
          "status": "production", 
          "type": "PerfSonar"
        }
      ], 
      "severity": "OUTAGE", 
      "site": "UNI-FREIBURG", 
      "site_id": 1230, 
      "start_time": "2018-08-13T20:00:00", 
      "state": "ACTIVE"
    }
  ], 
  "UNICPH-NBI": [
    {
      "affected_services": "ARC-CE", 
      "classification": "SCHEDULED", 
      "create_time": "2018-07-26T14:49:20", 
      "description": "CE down for complete rebuild and physical relocation. ", 
      "end_time": "2018-12-31T15:00:00", 
      "id": 124454, 
      "info_url": "https://goc.egi.eu/portal/index.php?Page_Type=Downtime&id=25743", 
      "is_published": false, 
      "last_modified": "2018-07-26T17:00:12.722141", 
      "last_published": null, 
      "pid": "104356G0", 
      "provider": "GOCDB", 
      "rc_site": "NDGF-T1", 
      "services": [], 
      "severity": "OUTAGE", 
      "site": "NDGF-T1", 
      "site_id": 1176, 
      "start_time": "2018-07-27T15:00:00", 
      "state": "ACTIVE"
    }, 
    {
      "affected_services": "ARC-CE", 
      "classification": "SCHEDULED", 
      "create_time": "2018-08-13T13:36:45", 
      "description": "Infiniband maintenance", 
      "end_time": "2018-09-10T23:59:00", 
      "id": 124540, 
      "info_url": "https://goc.egi.eu/portal/index.php?Page_Type=Downtime&id=25867", 
      "is_published": false, 
      "last_modified": "2018-08-13T15:45:07.192880", 
      "last_published": null, 
      "pid": "104480G0", 
      "provider": "GOCDB", 
      "rc_site": "NDGF-T1", 
      "services": [], 
      "severity": "OUTAGE", 
      "site": "NDGF-T1", 
      "site_id": 1176, 
      "start_time": "2018-09-10T00:00:00", 
      "state": "ACTIVE"
    }
  ]
}
